parrotfeeder/__init__.py
parrotfeeder/parrot_feeder.py
parrot_feeder-0.12.0.dist-info/LICENSE
parrot_feeder-0.12.0.dist-info/METADATA
parrot_feeder-0.12.0.dist-info/WHEEL
parrot_feeder-0.12.0.dist-info/entry_points.txt
parrot_feeder-0.12.0.dist-info/top_level.txt
parrot_feeder-0.12.0.dist-info/RECORD
