Metadata-Version: 2.1
Name: parrot-feeder
Version: 0.12.0
Summary: Advanced multi-channel file-sharing tool
Home-page: https://github.com/le-p0pug-labs/parrot-feeder
Author: LE POPUG
Author-email: fixions@protonmail.com
Project-URL: Bug Reports, https://github.com/le-p0pug-labs/parrot-feeder/issues
Project-URL: Source, https://github.com/le-p0pug-labs/parrot-feeder
Keywords: file-sharing,ngrok,flask
Classifier: Development Status :: 5 - Production/Stable
Classifier: Environment :: Console
Classifier: Intended Audience :: Information Technology
Classifier: Intended Audience :: Other Audience
Classifier: License :: OSI Approved :: MIT License
Classifier: Operating System :: POSIX :: Linux
Classifier: Operating System :: Microsoft :: Windows
Classifier: Programming Language :: Python :: 3
Classifier: Programming Language :: Python :: 3.6
Classifier: Programming Language :: Python :: 3.7
Classifier: Programming Language :: Python :: 3.8
Classifier: Programming Language :: Python :: 3.9
Classifier: Programming Language :: Python :: 3 :: Only
Requires-Python: >=3.6, <4
License-File: LICENSE
Requires-Dist: flask
Requires-Dist: flask-autoindex
Requires-Dist: pyngrok
Requires-Dist: python-telegram-bot
